{
  "db_name": "SQLite",
  "query": "\n        SELECT public_key as \"public_key!\", username, avatar_url, status_text,\n               ip_address, port, is_bootstrap, last_seen_at, first_seen_at\n        FROM peers\n        WHERE is_bootstrap = 1\n        ORDER BY last_seen_at DESC\n        ",
  "describe": {
    "columns": [
      {
        "name": "public_key!",
        "ordinal": 0,
        "type_info": "Text"
      },
      {
        "name": "username",
        "ordinal": 1,
        "type_info": "Text"
      },
      {
        "name": "avatar_url",
        "ordinal": 2,
        "type_info": "Text"
      },
      {
        "name": "status_text",
        "ordinal": 3,
        "type_info": "Text"
      },
      {
        "name": "ip_address",
        "ordinal": 4,
        "type_info": "Text"
      },
      {
        "name": "port",
        "ordinal": 5,
        "type_info": "Int64"
      },
      {
        "name": "is_bootstrap",
        "ordinal": 6,
        "type_info": "Int64"
      },
      {
        "name": "last_seen_at",
        "ordinal": 7,
        "type_info": "Text"
      },
      {
        "name": "first_seen_at",
        "ordinal": 8,
        "type_info": "Text"
      }
    ],
    "parameters": {
      "Right": 0
    },
    "nullable": [
      true,
      true,
      true,
      true,
      true,
      true,
      false,
      true,
      false
    ]
  },
  "hash": "2e3578475166da3c537d45dd0ef7fcb9370ca00b2b1a44f49fefd7fa3907f5de"
}
